{
  "extends": ["tslint-plugin-prettier", "tslint-config-prettier"],

  "rules": {
    "prettier": true,
    "class-name": true,
    "comment-format": [true, "check-space"],
    "no-var-keyword": true,
    "no-internal-module": true,
    "no-null-keyword": false,
    "prefer-const": true,
    "jsdoc-format": true,
    "prefer-object-spread": true,
    "no-string-throw": true,
    "no-return-await": true,
    "promise-function-async": false,
    "await-promise": true,
    "interface-name": false,
    "no-this-assignment": true,
    "arrow-return-shorthand": true,
    "adjacent-overload-signatures": true,
    "callable-types": true,
    "completed-docs": false
  }
}
